[
    {
        "key": "dbln",
        "value": "%7B%2261557988164733%22%3A%22EVnxtv7H%22%7D",
        "domain": "facebook.com",
        "path": "/login/device-based/",
        "hostOnly": false,
        "creation": "2025-01-18T17:41:38.029Z",
        "lastAccessed": "2025-01-18T17:41:38.030Z"
    },
    {
        "key": "sb",
        "value": "RSF_Z5ZhnNNnplW2RFHQ_uqQ",
        "domain": "facebook.com",
        "path": "/",
        "hostOnly": false,
        "creation": "2025-01-18T17:41:38.030Z",
        "lastAccessed": "2025-01-18T17:41:38.030Z"
    },
    {
        "key": "vpd",
        "value": "v1%3B674x360x2",
        "domain": "facebook.com",
        "path": "/",
        "hostOnly": false,
        "creation": "2025-01-18T17:41:38.030Z",
        "lastAccessed": "2025-01-18T17:41:38.030Z"
    },
    {
        "key": "ps_l",
        "value": "1",
        "domain": "facebook.com",
        "path": "/",
        "hostOnly": false,
        "creation": "2025-01-18T17:41:38.030Z",
        "lastAccessed": "2025-01-18T17:41:38.030Z"
    },
    {
        "key": "ps_n",
        "value": "1",
        "domain": "facebook.com",
        "path": "/",
        "hostOnly": false,
        "creation": "2025-01-18T17:41:38.030Z",
        "lastAccessed": "2025-01-18T17:41:38.030Z"
    },
    {
        "key": "wl_cbv",
        "value": "v2%3Bclient_version%3A2713%3Btimestamp%3A1736702543",
        "domain": "facebook.com",
        "path": "/",
        "hostOnly": false,
        "creation": "2025-01-18T17:41:38.030Z",
        "lastAccessed": "2025-01-18T17:41:38.030Z"
    },
    {
        "key": "dpr",
        "value": "2.1988937854766846",
        "domain": "facebook.com",
        "path": "/",
        "hostOnly": false,
        "creation": "2025-01-18T17:41:38.030Z",
        "lastAccessed": "2025-01-18T17:41:38.030Z"
    },
    {
        "key": "datr",
        "value": "5EqJZ6s-U14CCOh-AUS0LGKC",
        "domain": "facebook.com",
        "path": "/",
        "hostOnly": false,
        "creation": "2025-01-18T17:41:38.030Z",
        "lastAccessed": "2025-01-18T17:41:38.030Z"
    },
    {
        "key": "locale",
        "value": "en_GB",
        "domain": "facebook.com",
        "path": "/",
        "hostOnly": false,
        "creation": "2025-01-18T17:41:38.030Z",
        "lastAccessed": "2025-01-18T17:41:38.030Z"
    },
    {
        "key": "wd",
        "value": "891x1669",
        "domain": "facebook.com",
        "path": "/",
        "hostOnly": false,
        "creation": "2025-01-18T17:41:38.030Z",
        "lastAccessed": "2025-01-18T17:41:38.030Z"
    },
    {
        "key": "c_user",
        "value": "61557988164733",
        "domain": "facebook.com",
        "path": "/",
        "hostOnly": false,
        "creation": "2025-01-18T17:41:38.030Z",
        "lastAccessed": "2025-01-18T17:41:38.030Z"
    },
    {
        "key": "xs",
        "value": "17%3AVGcAsfn2XCGYWA%3A2%3A1737222091%3A-1%3A5903",
        "domain": "facebook.com",
        "path": "/",
        "hostOnly": false,
        "creation": "2025-01-18T17:41:38.030Z",
        "lastAccessed": "2025-01-18T17:41:38.030Z"
    },
    {
        "key": "fr",
        "value": "1frdW0HoO9H4szhBE.AWWurfLrYAIH6IfxqOJY11KAVZU.BniyBA..AAA.0.0.Bni-fM.AWWc7PBpWws",
        "domain": "facebook.com",
        "path": "/",
        "hostOnly": false,
        "creation": "2025-01-18T17:41:38.030Z",
        "lastAccessed": "2025-01-18T17:41:38.030Z"
    }
]
