[
    {
        "key": "dbln",
        "value": "%7B%2261573094946188%22%3A%22iuVEZew2%22%7D",
        "domain": "facebook.com",
        "path": "/login/device-based/",
        "hostOnly": false,
        "creation": "2025-03-18T16:35:59.979Z",
        "lastAccessed": "2025-03-18T16:35:59.986Z"
    },
    {
        "key": "sb",
        "value": "_xXSZ6-D-vsQ28gx0eavjhgM",
        "domain": "facebook.com",
        "path": "/",
        "hostOnly": false,
        "creation": "2025-03-18T16:35:59.986Z",
        "lastAccessed": "2025-03-18T16:35:59.986Z"
    },
    {
        "key": "locale",
        "value": "en_GB",
        "domain": "facebook.com",
        "path": "/",
        "hostOnly": false,
        "creation": "2025-03-18T16:35:59.986Z",
        "lastAccessed": "2025-03-18T16:35:59.986Z"
    },
    {
        "key": "ps_l",
        "value": "1",
        "domain": "facebook.com",
        "path": "/",
        "hostOnly": false,
        "creation": "2025-03-18T16:35:59.986Z",
        "lastAccessed": "2025-03-18T16:35:59.986Z"
    },
    {
        "key": "ps_n",
        "value": "1",
        "domain": "facebook.com",
        "path": "/",
        "hostOnly": false,
        "creation": "2025-03-18T16:35:59.986Z",
        "lastAccessed": "2025-03-18T16:35:59.986Z"
    },
    {
        "key": "dpr",
        "value": "2.1988937854766846",
        "domain": "facebook.com",
        "path": "/",
        "hostOnly": false,
        "creation": "2025-03-18T16:35:59.986Z",
        "lastAccessed": "2025-03-18T16:35:59.986Z"
    },
    {
        "key": "datr",
        "value": "2A_WZ922WUOh2kLMTRkfXL7g",
        "domain": "facebook.com",
        "path": "/",
        "hostOnly": false,
        "creation": "2025-03-18T16:35:59.986Z",
        "lastAccessed": "2025-03-18T16:35:59.986Z"
    },
    {
        "key": "vpd",
        "value": "v1%3B674x360x2",
        "domain": "facebook.com",
        "path": "/",
        "hostOnly": false,
        "creation": "2025-03-18T16:35:59.986Z",
        "lastAccessed": "2025-03-18T16:35:59.986Z"
    },
    {
        "key": "m_pixel_ratio",
        "value": "2",
        "domain": "facebook.com",
        "path": "/",
        "hostOnly": false,
        "creation": "2025-03-18T16:35:59.986Z",
        "lastAccessed": "2025-03-18T16:35:59.986Z"
    },
    {
        "key": "c_user",
        "value": "61573094946188",
        "domain": "facebook.com",
        "path": "/",
        "hostOnly": false,
        "creation": "2025-03-18T16:35:59.986Z",
        "lastAccessed": "2025-03-18T16:35:59.986Z"
    },
    {
        "key": "fr",
        "value": "1OHCKjxssXxrTSTHm.AWWMk81khK0tds0F1QPA8gVKVzxIqN6EJlarTg.Bn1khz..AAA.0.0.Bn2Zle.AWW1bnPUESs",
        "domain": "facebook.com",
        "path": "/",
        "hostOnly": false,
        "creation": "2025-03-18T16:35:59.986Z",
        "lastAccessed": "2025-03-18T16:35:59.986Z"
    },
    {
        "key": "xs",
        "value": "10%3AjeMDBbJEI8tGhQ%3A2%3A1742313823%3A-1%3A-1",
        "domain": "facebook.com",
        "path": "/",
        "hostOnly": false,
        "creation": "2025-03-18T16:35:59.986Z",
        "lastAccessed": "2025-03-18T16:35:59.986Z"
    },
    {
        "key": "wd",
        "value": "360x674",
        "domain": "facebook.com",
        "path": "/",
        "hostOnly": false,
        "creation": "2025-03-18T16:35:59.986Z",
        "lastAccessed": "2025-03-18T16:35:59.986Z"
    },
    {
        "key": "wl_cbv",
        "value": "v2%3Bclient_version%3A2764%3Btimestamp%3A1742313840",
        "domain": "facebook.com",
        "path": "/",
        "hostOnly": false,
        "creation": "2025-03-18T16:35:59.986Z",
        "lastAccessed": "2025-03-18T16:35:59.986Z"
    },
    {
        "key": "fbl_st",
        "value": "101535451%3BT%3A29038595",
        "domain": "facebook.com",
        "path": "/",
        "hostOnly": false,
        "creation": "2025-03-18T16:35:59.986Z",
        "lastAccessed": "2025-03-18T16:35:59.986Z"
    }
]
