[
    {
        "key": "dbln",
        "value": "%7B%22100086067772297%22%3A%22idJZAL8Y%22%2C%2261565847252426%22%3A%22jAw1qne2%22%2C%2261559958515207%22%3A%2286myaoc0%22%2C%2261566411242730%22%3A%22kSHtAZpv%22%2C%2261567343891178%22%3A%22orfF3DWq%22%2C%2261557988164733%22%3A%22i1e3GIxD%22%2C%22100003207296983%22%3A%223sLpCcdu%22%7D",
        "domain": "facebook.com",
        "path": "/login/device-based/",
        "hostOnly": false,
        "creation": "2024-12-02T15:51:05.012Z",
        "lastAccessed": "2024-12-02T15:51:05.013Z"
    },
    {
        "key": "sb",
        "value": "u_ylZn2eXWUVsSd46Y5Y41UE",
        "domain": "facebook.com",
        "path": "/",
        "hostOnly": false,
        "creation": "2024-12-02T15:51:05.013Z",
        "lastAccessed": "2024-12-02T15:51:05.014Z"
    },
    {
        "key": "vpd",
        "value": "v1%3B674x360x2",
        "domain": "facebook.com",
        "path": "/",
        "hostOnly": false,
        "creation": "2024-12-02T15:51:05.014Z",
        "lastAccessed": "2024-12-02T15:51:05.014Z"
    },
    {
        "key": "ps_l",
        "value": "1",
        "domain": "facebook.com",
        "path": "/",
        "hostOnly": false,
        "creation": "2024-12-02T15:51:05.014Z",
        "lastAccessed": "2024-12-02T15:51:05.014Z"
    },
    {
        "key": "ps_n",
        "value": "1",
        "domain": "facebook.com",
        "path": "/",
        "hostOnly": false,
        "creation": "2024-12-02T15:51:05.014Z",
        "lastAccessed": "2024-12-02T15:51:05.014Z"
    },
    {
        "key": "datr",
        "value": "MWzuZta8li7LrRt14AoFF8QZ",
        "domain": "facebook.com",
        "path": "/",
        "hostOnly": false,
        "creation": "2024-12-02T15:51:05.014Z",
        "lastAccessed": "2024-12-02T15:51:05.014Z"
    },
    {
        "key": "dpr",
        "value": "2.1988937854766846",
        "domain": "facebook.com",
        "path": "/",
        "hostOnly": false,
        "creation": "2024-12-02T15:51:05.014Z",
        "lastAccessed": "2024-12-02T15:51:05.014Z"
    },
    {
        "key": "locale",
        "value": "en_GB",
        "domain": "facebook.com",
        "path": "/",
        "hostOnly": false,
        "creation": "2024-12-02T15:51:05.014Z",
        "lastAccessed": "2024-12-02T15:51:05.014Z"
    },
    {
        "key": "wd",
        "value": "360x674",
        "domain": "facebook.com",
        "path": "/",
        "hostOnly": false,
        "creation": "2024-12-02T15:51:05.014Z",
        "lastAccessed": "2024-12-02T15:51:05.014Z"
    },
    {
        "key": "c_user",
        "value": "100001826406323",
        "domain": "facebook.com",
        "path": "/",
        "hostOnly": false,
        "creation": "2024-12-02T15:51:05.014Z",
        "lastAccessed": "2024-12-02T15:51:05.014Z"
    },
    {
        "key": "fr",
        "value": "1fokMx7H2r5UjAmbj.AWWUarakFzGeg_NH2AEWU8W3hhw.BnRTyV..AAA.0.0.BnTUxZ.AWUZpFjxDHQ",
        "domain": "facebook.com",
        "path": "/",
        "hostOnly": false,
        "creation": "2024-12-02T15:51:05.014Z",
        "lastAccessed": "2024-12-02T15:51:05.014Z"
    },
    {
        "key": "xs",
        "value": "48%3A7LNVnU3kRz7R0g%3A2%3A1733119065%3A-1%3A13588",
        "domain": "facebook.com",
        "path": "/",
        "hostOnly": false,
        "creation": "2024-12-02T15:51:05.014Z",
        "lastAccessed": "2024-12-02T15:51:05.014Z"
    },
    {
        "key": "fbl_st",
        "value": "100622190%3BT%3A28885909",
        "domain": "facebook.com",
        "path": "/",
        "hostOnly": false,
        "creation": "2024-12-02T15:51:05.014Z",
        "lastAccessed": "2024-12-02T15:51:05.014Z"
    },
    {
        "key": "wl_cbv",
        "value": "v2%3Bclient_version%3A2682%3Btimestamp%3A1733154600",
        "domain": "facebook.com",
        "path": "/",
        "hostOnly": false,
        "creation": "2024-12-02T15:51:05.014Z",
        "lastAccessed": "2024-12-02T15:51:05.014Z"
    }
]
