[
    {
        "key": "dbln",
        "value": "%7B%22100090438977548%22%3A%227FPy99E9%22%7D",
        "domain": "facebook.com",
        "path": "/login/device-based/",
        "hostOnly": false,
        "creation": "2025-04-12T15:45:23.692Z",
        "lastAccessed": "2025-04-12T15:45:23.692Z"
    },
    {
        "key": "sb",
        "value": "KuOqZzMu6sjRvLde12Ho3xHU",
        "domain": "facebook.com",
        "path": "/",
        "hostOnly": false,
        "creation": "2025-04-12T15:45:23.692Z",
        "lastAccessed": "2025-04-12T15:45:23.692Z"
    },
    {
        "key": "ps_l",
        "value": "1",
        "domain": "facebook.com",
        "path": "/",
        "hostOnly": false,
        "creation": "2025-04-12T15:45:23.693Z",
        "lastAccessed": "2025-04-12T15:45:23.693Z"
    },
    {
        "key": "ps_n",
        "value": "1",
        "domain": "facebook.com",
        "path": "/",
        "hostOnly": false,
        "creation": "2025-04-12T15:45:23.693Z",
        "lastAccessed": "2025-04-12T15:45:23.693Z"
    },
    {
        "key": "datr",
        "value": "O1_5Z8-YdjcIAY2VroYsDYEI",
        "domain": "facebook.com",
        "path": "/",
        "hostOnly": false,
        "creation": "2025-04-12T15:45:23.693Z",
        "lastAccessed": "2025-04-12T15:45:23.693Z"
    },
    {
        "key": "wd",
        "value": "980x1704",
        "domain": "facebook.com",
        "path": "/",
        "hostOnly": false,
        "creation": "2025-04-12T15:45:23.693Z",
        "lastAccessed": "2025-04-12T15:45:23.693Z"
    },
    {
        "key": "c_user",
        "value": "100001826406323",
        "domain": "facebook.com",
        "path": "/",
        "hostOnly": false,
        "creation": "2025-04-12T15:45:23.693Z",
        "lastAccessed": "2025-04-12T15:45:23.693Z"
    },
    {
        "key": "xs",
        "value": "33%3At5l2W_zzdBwE-A%3A2%3A1744396111%3A-1%3A13588%3A%3AAcVQZJurrFxUhUDay9K6pUHdxQa-oMk8rCN2vuoTuA",
        "domain": "facebook.com",
        "path": "/",
        "hostOnly": false,
        "creation": "2025-04-12T15:45:23.693Z",
        "lastAccessed": "2025-04-12T15:45:23.693Z"
    },
    {
        "key": "fr",
        "value": "1V0RRYKCU2NLWR8UP.AWcI8XRaeeeV7vPjc5q43S42thKdTmnUzRJ5nFeFauu41KvKjuI.Bn-oqC..AAA.0.0.Bn-oqF.AWchIRBgh_UVTCnK42Evbv3J7DY",
        "domain": "facebook.com",
        "path": "/",
        "hostOnly": false,
        "creation": "2025-04-12T15:45:23.693Z",
        "lastAccessed": "2025-04-12T15:45:23.693Z"
    },
    {
        "key": "presence",
        "value": "C%7B%22t3%22%3A%5B%5D%2C%22utc3%22%3A1744472720504%2C%22v%22%3A1%7D",
        "domain": "facebook.com",
        "path": "/",
        "hostOnly": false,
        "creation": "2025-04-12T15:45:23.693Z",
        "lastAccessed": "2025-04-12T15:45:23.693Z"
    }
]
